Workbook
Name A: [1]ISR!#REF!
Name A: [1]ISR!#REF!
Name AS: [1]ISR!#REF!
Name AS: [1]ISR!#REF!
Name B: [2]ISR!#REF!
Name B: [2]ISR!#REF!
Name CREDITOS: [1]ISR!#REF!
Name CREDITOS: [1]ISR!#REF!
Name CREDITOS: [1]ISR!#REF!
Name CREDITOS: [1]ISR!#REF!
Name CREDITOS02: [1]CREDITOS!#REF!
Name CREDITOS02: [1]CREDITOS!#REF!
Name CREDITOS02: [1]CREDITOS!#REF!
Name CREDITOS02: [1]CREDITOS!#REF!
Name CREDITOSIMPAC: [1]ISR!#REF!
Name CREDITOSIMPAC: [1]ISR!#REF!
Name CREDITOSIMPAC: [1]ISR!#REF!
Name CREDITOSIMPAC: [1]ISR!#REF!
Name D: [1]ISR!#REF!
Name D: [1]ISR!#REF!
Name DEUDAS: [1]ISR!#REF!
Name DEUDAS: [1]ISR!#REF!
Name DEUDAS: [1]ISR!#REF!
Name DEUDAS: [1]ISR!#REF!
Name DISEÑO: [1]ISR!#REF!
Name DISEÑO: [1]ISR!#REF!
Name DISEÑO: [1]ISR!#REF!
Name DISEÑO: [1]ISR!#REF!
Name E: [1]ISR!#REF!
Name E: [1]ISR!#REF!
Name HOJA: [1]ISR!#REF!
Name HOJA: [1]ISR!#REF!
Name HOJA: [1]ISR!#REF!
Name HOJA1: [1]CREDITOS!#REF!
Name HOJA1: [1]CREDITOS!#REF!
Name HOJA1: [1]CREDITOS!#REF!
Name INTERESES: [2]ISR!#REF!
Name INTERESES: [2]ISR!#REF!
Name INTERESES: [2]ISR!#REF!
Name INTERESES: [2]ISR!#REF!
Name OTROS_DATOS: #REF!
Name OTROS_DATOS: #REF!
Name OTROS_DATOS: #REF!
Name OTROS_DATOS: #REF!
Name RESUMEN_IMPAC: #REF!
Name RESUMEN_IMPAC: #REF!
Name RESUMEN_IMPAC: #REF!
Name RESUMEN_IMPAC: #REF!

Sheet TABLAS
A2: TARIFA ACTUALIZADA DEL IMPUESTO CORRESPONDIENTE AL EJERCICIO DE 2026
A3: TARIFA PARA EL CALCULO DEL EJERCICIO 2026
G4: BASE GRAVABLE | H4: 39961.72
A5: TARIFA MENSUAL 2026 | F5: (-) | G5: LIMITE INFERIOR | H5: =+VLOOKUP(H4,$A$7:$D$17,1) -> 35362.84
A6: LIMITE INFERIOR | B6: LIMITE SUPERIOR | C6: CUOTA FIJA | D6: % EXC. LIMITE INF. | G6: EXED. S/LIM. INFERIOR | H6: =+H4-H5 -> 4598.88
A7: 0.01 | B7: 844.59 | C7: 0 | D7: 0.0192 | F7: (x) | G7: % S/EXED. LIM. INF. | H7: =+VLOOKUP(H4,$A$7:$D$17,4) -> 0.2352
A8: 844.6 | B8: 7168.51 | C8: 16.22 | D8: 0.064 | G8: IMPUESTO MARGINAL | H8: =H6*H7 -> 1081.6566
A9: 7168.52 | B9: 12598.02 | C9: 420.95 | D9: 0.1088 | F9: (+) | G9: CUOTA FIJA | H9: =+VLOOKUP(H4,$A$7:$D$17,3) -> 5665.16
A10: 12598.03 | B10: 14644.64 | C10: 1011.68 | D10: 0.16 | G10: IMPUESTO CAUSADO 113 | H10: =+H8+H9 -> 6746.8166
A11: 14644.65 | B11: 17533.64 | C11: 1339.14 | D11: 0.1792 | F11: (-) | G11: SUBSIDIO PARA EL EMPLEO | H11: 0
A12: 17533.65 | B12: 35362.83 | C12: 1856.84 | D12: 0.2136 | G12: IMPUESTO A RETENER | H12: =+H10-H11 -> 6746.8166
A13: 35362.84 | B13: 55736.68 | C13: 5665.16 | D13: 0.2352
A14: 55736.69 | B14: 106410.5 | C14: 10457.09 | D14: 0.3
A15: 106410.51 | B15: 141880.66 | C15: 25659.23 | D15: 0.32
A16: 141880.67 | B16: 425641.99 | C16: 37009.69 | D16: 0.34
A17: 425642 | B17: EN ADELANTE | C17: 133488.54 | D17: 0.35
A43: 1.00 Salario mínimo (SM) | B43: 0 | C43: 207.44 | D43: 0.0315
A44: 1.01 SM a 1.50 UMA | B44: 103.74 | C44: =+B44*1.5 -> 155.61 | D44: 0.03281
A45: 1.51 a 2.00 UMA | B45: =+C44+0.01 -> 155.62 | C45: =+B44*2 -> 207.48 | D45: 0.03575
A46: 2.01 a 2.50 UMA | B46: =+C45+0.01 -> 207.49 | C46: =+B44*2.5 -> 259.35 | D46: 0.03751
A47: 2.51 a 3.00 UMA | B47: =+C46+0.01 -> 259.36 | C47: =+B44*3 -> 311.22 | D47: 0.03869
A48: 3.01 a 3.50 UMA | B48: =+C47+0.01 -> 311.23 | C48: =+B44*3.5 -> 363.09 | D48: 0.03953
A49: 3.51 a 4.00 UMA | B49: =+C48+0.01 -> 363.1 | C49: =+B44*4 -> 414.96 | D49: 0.04016
A50: 4.01 UMA en adelante | B50: =+C49+0.01 -> 414.97 | C50: 10000 | D50: 0.04241

Sheet CALCULO
C2: PROPUESTA SC
E3: 207.44 | F3: =ROUND(E3*1.5,2) -> 311.16
A4: N° | B4: NOMBRE | C4: CLAVE | D4: TOTAL A CONSIDERAR | E4: REMANENTE | F4: ART 96 | G4: TOTAL NETO REMANENTE | H4: NO OBJETO | I4: TOTAL A DEPOSITAR | J4: MONEDERO
A6: 1 | B6: Empleado 1 | C6: Emp 001 | E6: =D6*20% -> 0 | F6: =(E6-VLOOKUP(E6,TABLAS!$A$7:$D$17,1))*VLOOKUP(E6,TABLAS!$A$7:$D$17,4)+VLOOKUP(E6,TABLAS!$A$7:$D$17,3) -> #N/A | G6: =E6-F6 -> #N/A | H6: =D6-E6 -> 0 | I6: =G6+H6 -> #N/A
A7: =A6+1 -> 2 | B7: Empleado 2 | C7: Emp 002 | E7: =D7*20% -> 0 | F7: =(E7-VLOOKUP(E7,TABLAS!$A$7:$D$17,1))*VLOOKUP(E7,TABLAS!$A$7:$D$17,4)+VLOOKUP(E7,TABLAS!$A$7:$D$17,3) -> #N/A | G7: =E7-F7 -> #N/A | H7: =D7-E7 -> 0 | I7: =G7+H7 -> #N/A
A8: =A7+1 -> 3 | B8: Empleado 3 | C8: Emp 003 | E8: =D8*20% -> 0 | F8: =(E8-VLOOKUP(E8,TABLAS!$A$7:$D$17,1))*VLOOKUP(E8,TABLAS!$A$7:$D$17,4)+VLOOKUP(E8,TABLAS!$A$7:$D$17,3) -> #N/A | G8: =E8-F8 -> #N/A | H8: =D8-E8 -> 0 | I8: =G8+H8 -> #N/A
B11: SUMA | D11: =SUM(D6:D8) -> 0 | E11: =SUM(E6:E8) -> 0 | F11: =SUM(F6:F8) -> #N/A | G11: =SUM(G6:G8) -> #N/A | H11: =SUM(H6:H8) -> 0 | I11: =SUM(I6:I8) -> #N/A | J11: =SUM(#REF!) -> #REF!
D13: DESGLOCE FACTURA
D14: TOTAL SC | F14: =D11 -> 0
D16: COSTO COMISIÓN | E16: 0.06 | F16: =F14*E16 -> 0
D18: SUBTOTAL | F18: =F14+F16 -> 0
D19: IVA | E19: 0.16 | F19: =F18*E19 -> 0
D20: TOTAL GLOBAL FACTURA | F20: =F18+F19 -> 0

Sheet IMSS
L1: SMGDF | M1: 3 SMGDF
A2: MC | L2: 103.74 | M2: =+L2*3 -> 311.22 | R2: =+H8*M8 -> #REF! | S2: 1
R3: =+R8 -> #REF! | S3: 0.053344
N4: ENFERMEDADES Y MATERNIDAD | V4: < | AB4: COSTO SOCIAL | AG4: INGRESO | AJ4: UITILIDAD
A5: N° | F5: NOMBRE | G5: CLAVE | H5: DIAS | I5: DIAS COTIZADOS | J5: DIAS INCAPACIDAD | K5: DIAS AUSENTISMO | L5: SALARIO DIARIO | M5: SBC | N5: CUOTA FIJA | O5: EXCEDENTE | P5: PREST EN DINERO | Q5: PREST EN ESPECIE | R5: RIESGO DE TRAB | S5: INVALIDEZ Y VIDA | T5: GUARDERIAS | U5: TOTAL IMSS MENSUAL | W5: RETIRO | X5: CESANTIA Y VEJEZ | Y5: INFONAVIT | Z5: TOTAL BIMESTRAL | AB5: TOTAL MENSUAL | AC5: TOTAL RCV E INF | AD5: 3% NOMINA | AE5: TOTAL COSTO | AG5: INGRESO | AH5: IVA | AI5: TOTAL INGRESO | AK5: COSTO POR PERIODO | AL5: COSTO POR DIA
N6: 0.204 | O6: 0.015 | P6: 0.0095 | Q6: 0.01425 | R6: 0.0054355 | S6: 0.02375 | T6: 0.01 | W6: 0.02 | Y6: 0.05
A8: 1 | F8: =CALCULO!#REF! -> #REF! | G8: =CALCULO!#REF! -> #REF! | H8: =+I8-J8-K8 -> 31 | I8: 31 | J8: 0 | K8: 0 | L8: =+CALCULO!#REF! -> #REF! | M8: =IF(L8*1.0493>$L$2*25,$L$2*25,L8*1.0493) -> #REF! | N8: =+ROUND($L$2*$N$6*I8,2) -> 656.05 | O8: =+IF(M8>$M$2,M8-$M$2,0)*$O$6*I8 -> #REF! | P8: =+ROUND(M8*$P$6*I8,2) -> #REF! | Q8: =+ROUND(M8*$Q$6*I8,2) -> #REF! | R8: =+ROUND(M8*$R$6*I8,2) -> #REF! | S8: =+ROUND(M8*$S$6*I8,2) -> #REF! | T8: =+ROUND(M8*$T$6*I8,2) -> #REF! | U8: =+SUM(N8:T8) -> #REF! | W8: =+ROUND(I8*M8*$W$6,2) -> #REF! | X8: =+ROUND(H8*M8*(VLOOKUP(M8,TABLAS!$B$44:$D$50,3,1)+1.125%),2) -> #REF! | Y8: =+ROUND(H8*M8*$Y$6,2) -> #REF! | Z8: =+SUM(W8:Y8) -> #REF! | AB8: =+U8 -> #REF! | AC8: =+Z8 -> #REF! | AD8: =+H8*L8*3% -> #REF! | AE8: =+SUM(AB8:AD8) -> #REF! | AG8: =+AE8+AJ8 -> #REF! | AH8: =+AG8*16% -> #REF! | AI8: =+AG8+AH8 -> #REF! | AJ8: =+AE8*7.21% -> #REF! | AK8: =AL8*31 -> #REF! | AL8: =AE8/30.4 -> #REF!
A9: =+A8+1 -> 2 | F9: =CALCULO!#REF! -> #REF! | G9: =CALCULO!#REF! -> #REF! | H9: =+I9-J9-K9 -> 31 | I9: 31 | J9: 0 | K9: 0 | L9: =+CALCULO!#REF! -> #REF! | M9: =IF(L9*1.0493>$L$2*25,$L$2*25,L9*1.0493) -> #REF! | N9: =+ROUND($L$2*$N$6*I9,2) -> 656.05 | O9: =+IF(M9>$M$2,M9-$M$2,0)*$O$6*I9 -> #REF! | P9: =+ROUND(M9*$P$6*I9,2) -> #REF! | Q9: =+ROUND(M9*$Q$6*I9,2) -> #REF! | R9: =+ROUND(M9*$R$6*I9,2) -> #REF! | S9: =+ROUND(M9*$S$6*I9,2) -> #REF! | T9: =+ROUND(M9*$T$6*I9,2) -> #REF! | U9: =+SUM(N9:T9) -> #REF! | W9: =+ROUND(I9*M9*$W$6,2) -> #REF! | X9: =+ROUND(H9*M9*(VLOOKUP(M9,TABLAS!$B$44:$D$50,3,1)+1.125%),2) -> #REF! | Y9: =+ROUND(H9*M9*$Y$6,2) -> #REF! | Z9: =+SUM(W9:Y9) -> #REF! | AB9: =+U9 -> #REF! | AC9: =+Z9 -> #REF! | AD9: =+H9*L9*3% -> #REF! | AE9: =+SUM(AB9:AD9) -> #REF! | AG9: =+AE9+AJ9 -> #REF! | AH9: =+AG9*16% -> #REF! | AI9: =+AG9+AH9 -> #REF! | AJ9: =+AE9*7.21% -> #REF! | AK9: =AL9*31 -> #REF! | AL9: =AE9/30.4 -> #REF!
A10: =+A9+1 -> 3 | F10: =CALCULO!#REF! -> #REF! | G10: =CALCULO!#REF! -> #REF! | H10: =+I10-J10-K10 -> 31 | I10: 31 | J10: 0 | K10: 0 | L10: =+CALCULO!#REF! -> #REF! | M10: =IF(L10*1.0493>$L$2*25,$L$2*25,L10*1.0493) -> #REF! | N10: =+ROUND($L$2*$N$6*I10,2) -> 656.05 | O10: =+IF(M10>$M$2,M10-$M$2,0)*$O$6*I10 -> #REF! | P10: =+ROUND(M10*$P$6*I10,2) -> #REF! | Q10: =+ROUND(M10*$Q$6*I10,2) -> #REF! | R10: =+ROUND(M10*$R$6*I10,2) -> #REF! | S10: =+ROUND(M10*$S$6*I10,2) -> #REF! | T10: =+ROUND(M10*$T$6*I10,2) -> #REF! | U10: =+SUM(N10:T10) -> #REF! | W10: =+ROUND(I10*M10*$W$6,2) -> #REF! | X10: =+ROUND(H10*M10*(VLOOKUP(M10,TABLAS!$B$44:$D$50,3,1)+1.125%),2) -> #REF! | Y10: =+ROUND(H10*M10*$Y$6,2) -> #REF! | Z10: =+SUM(W10:Y10) -> #REF! | AB10: =+U10 -> #REF! | AC10: =+Z10 -> #REF! | AD10: =+H10*L10*3% -> #REF! | AE10: =+SUM(AB10:AD10) -> #REF! | AG10: =+AE10+AJ10 -> #REF! | AH10: =+AG10*16% -> #REF! | AI10: =+AG10+AH10 -> #REF! | AJ10: =+AE10*7.21% -> #REF! | AK10: =AL10*31 -> #REF! | AL10: =AE10/30.4 -> #REF!
A11: =+A10+1 -> 4 | F11: =CALCULO!#REF! -> #REF! | G11: =CALCULO!#REF! -> #REF! | H11: =+I11-J11-K11 -> 31 | I11: 31 | J11: 0 | K11: 0 | L11: =+CALCULO!#REF! -> #REF! | M11: =IF(L11*1.0493>$L$2*25,$L$2*25,L11*1.0493) -> #REF! | N11: =+ROUND($L$2*$N$6*I11,2) -> 656.05 | O11: =+IF(M11>$M$2,M11-$M$2,0)*$O$6*I11 -> #REF! | P11: =+ROUND(M11*$P$6*I11,2) -> #REF! | Q11: =+ROUND(M11*$Q$6*I11,2) -> #REF! | R11: =+ROUND(M11*$R$6*I11,2) -> #REF! | S11: =+ROUND(M11*$S$6*I11,2) -> #REF! | T11: =+ROUND(M11*$T$6*I11,2) -> #REF! | U11: =+SUM(N11:T11) -> #REF! | W11: =+ROUND(I11*M11*$W$6,2) -> #REF! | X11: =+ROUND(H11*M11*(VLOOKUP(M11,TABLAS!$B$44:$D$50,3,1)+1.125%),2) -> #REF! | Y11: =+ROUND(H11*M11*$Y$6,2) -> #REF! | Z11: =+SUM(W11:Y11) -> #REF! | AB11: =+U11 -> #REF! | AC11: =+Z11 -> #REF! | AD11: =+H11*L11*3% -> #REF! | AE11: =+SUM(AB11:AD11) -> #REF! | AG11: =+AE11+AJ11 -> #REF! | AH11: =+AG11*16% -> #REF! | AI11: =+AG11+AH11 -> #REF! | AJ11: =+AE11*7.21% -> #REF! | AK11: =AL11*31 -> #REF! | AL11: =AE11/30.4 -> #REF!
A12: =+A11+1 -> 5 | F12: =CALCULO!#REF! -> #REF! | G12: =CALCULO!#REF! -> #REF! | H12: =+I12-J12-K12 -> 31 | I12: 31 | J12: 0 | K12: 0 | L12: =+CALCULO!#REF! -> #REF! | M12: =IF(L12*1.0493>$L$2*25,$L$2*25,L12*1.0493) -> #REF! | N12: =+ROUND($L$2*$N$6*I12,2) -> 656.05 | O12: =+IF(M12>$M$2,M12-$M$2,0)*$O$6*I12 -> #REF! | P12: =+ROUND(M12*$P$6*I12,2) -> #REF! | Q12: =+ROUND(M12*$Q$6*I12,2) -> #REF! | R12: =+ROUND(M12*$R$6*I12,2) -> #REF! | S12: =+ROUND(M12*$S$6*I12,2) -> #REF! | T12: =+ROUND(M12*$T$6*I12,2) -> #REF! | U12: =+SUM(N12:T12) -> #REF! | W12: =+ROUND(I12*M12*$W$6,2) -> #REF! | X12: =+ROUND(H12*M12*(VLOOKUP(M12,TABLAS!$B$44:$D$50,3,1)+1.125%),2) -> #REF! | Y12: =+ROUND(H12*M12*$Y$6,2) -> #REF! | Z12: =+SUM(W12:Y12) -> #REF! | AB12: =+U12 -> #REF! | AC12: =+Z12 -> #REF! | AD12: =+H12*L12*3% -> #REF! | AE12: =+SUM(AB12:AD12) -> #REF! | AG12: =+AE12+AJ12 -> #REF! | AH12: =+AG12*16% -> #REF! | AI12: =+AG12+AH12 -> #REF! | AJ12: =+AE12*7.21% -> #REF! | AK12: =AL12*31 -> #REF! | AL12: =AE12/30.4 -> #REF!
A13: =+A12+1 -> 6 | F13: =CALCULO!#REF! -> #REF! | G13: =CALCULO!#REF! -> #REF! | H13: =+I13-J13-K13 -> 31 | I13: 31 | J13: 0 | K13: 0 | L13: =+CALCULO!#REF! -> #REF! | M13: =IF(L13*1.0493>$L$2*25,$L$2*25,L13*1.0493) -> #REF! | N13: =+ROUND($L$2*$N$6*I13,2) -> 656.05 | O13: =+IF(M13>$M$2,M13-$M$2,0)*$O$6*I13 -> #REF! | P13: =+ROUND(M13*$P$6*I13,2) -> #REF! | Q13: =+ROUND(M13*$Q$6*I13,2) -> #REF! | R13: =+ROUND(M13*$R$6*I13,2) -> #REF! | S13: =+ROUND(M13*$S$6*I13,2) -> #REF! | T13: =+ROUND(M13*$T$6*I13,2) -> #REF! | U13: =+SUM(N13:T13) -> #REF! | W13: =+ROUND(I13*M13*$W$6,2) -> #REF! | X13: =+ROUND(H13*M13*(VLOOKUP(M13,TABLAS!$B$44:$D$50,3,1)+1.125%),2) -> #REF! | Y13: =+ROUND(H13*M13*$Y$6,2) -> #REF! | Z13: =+SUM(W13:Y13) -> #REF! | AB13: =+U13 -> #REF! | AC13: =+Z13 -> #REF! | AD13: =+H13*L13*3% -> #REF! | AE13: =+SUM(AB13:AD13) -> #REF! | AG13: =+AE13+AJ13 -> #REF! | AH13: =+AG13*16% -> #REF! | AI13: =+AG13+AH13 -> #REF! | AJ13: =+AE13*7.21% -> #REF! | AK13: =AL13*31 -> #REF! | AL13: =AE13/30.4 -> #REF!
A14: =+A13+1 -> 7 | F14: =CALCULO!#REF! -> #REF! | G14: =CALCULO!#REF! -> #REF! | H14: =+I14-J14-K14 -> 31 | I14: 31 | J14: 0 | K14: 0 | L14: =+CALCULO!#REF! -> #REF! | M14: =IF(L14*1.0493>$L$2*25,$L$2*25,L14*1.0493) -> #REF! | N14: =+ROUND($L$2*$N$6*I14,2) -> 656.05 | O14: =+IF(M14>$M$2,M14-$M$2,0)*$O$6*I14 -> #REF! | P14: =+ROUND(M14*$P$6*I14,2) -> #REF! | Q14: =+ROUND(M14*$Q$6*I14,2) -> #REF! | R14: =+ROUND(M14*$R$6*I14,2) -> #REF! | S14: =+ROUND(M14*$S$6*I14,2) -> #REF! | T14: =+ROUND(M14*$T$6*I14,2) -> #REF! | U14: =+SUM(N14:T14) -> #REF! | W14: =+ROUND(I14*M14*$W$6,2) -> #REF! | X14: =+ROUND(H14*M14*(VLOOKUP(M14,TABLAS!$B$44:$D$50,3,1)+1.125%),2) -> #REF! | Y14: =+ROUND(H14*M14*$Y$6,2) -> #REF! | Z14: =+SUM(W14:Y14) -> #REF! | AB14: =+U14 -> #REF! | AC14: =+Z14 -> #REF! | AD14: =+H14*L14*3% -> #REF! | AE14: =+SUM(AB14:AD14) -> #REF! | AG14: =+AE14+AJ14 -> #REF! | AH14: =+AG14*16% -> #REF! | AI14: =+AG14+AH14 -> #REF! | AJ14: =+AE14*7.21% -> #REF! | AK14: =AL14*31 -> #REF! | AL14: =AE14/30.4 -> #REF!
A15: =+A14+1 -> 8 | F15: =CALCULO!#REF! -> #REF! | G15: =CALCULO!#REF! -> #REF! | H15: =+I15-J15-K15 -> 31 | I15: 31 | J15: 0 | K15: 0 | L15: =+CALCULO!#REF! -> #REF! | M15: =IF(L15*1.0493>$L$2*25,$L$2*25,L15*1.0493) -> #REF! | N15: =+ROUND($L$2*$N$6*I15,2) -> 656.05 | O15: =+IF(M15>$M$2,M15-$M$2,0)*$O$6*I15 -> #REF! | P15: =+ROUND(M15*$P$6*I15,2) -> #REF! | Q15: =+ROUND(M15*$Q$6*I15,2) -> #REF! | R15: =+ROUND(M15*$R$6*I15,2) -> #REF! | S15: =+ROUND(M15*$S$6*I15,2) -> #REF! | T15: =+ROUND(M15*$T$6*I15,2) -> #REF! | U15: =+SUM(N15:T15) -> #REF! | W15: =+ROUND(I15*M15*$W$6,2) -> #REF! | X15: =+ROUND(H15*M15*(VLOOKUP(M15,TABLAS!$B$44:$D$50,3,1)+1.125%),2) -> #REF! | Y15: =+ROUND(H15*M15*$Y$6,2) -> #REF! | Z15: =+SUM(W15:Y15) -> #REF! | AB15: =+U15 -> #REF! | AC15: =+Z15 -> #REF! | AD15: =+H15*L15*3% -> #REF! | AE15: =+SUM(AB15:AD15) -> #REF! | AG15: =+AE15+AJ15 -> #REF! | AH15: =+AG15*16% -> #REF! | AI15: =+AG15+AH15 -> #REF! | AJ15: =+AE15*7.21% -> #REF! | AK15: =AL15*31 -> #REF! | AL15: =AE15/30.4 -> #REF!
A16: =+A15+1 -> 9 | F16: =CALCULO!#REF! -> #REF! | G16: =CALCULO!#REF! -> #REF! | H16: =+I16-J16-K16 -> 31 | I16: 31 | J16: 0 | K16: 0 | L16: =+CALCULO!#REF! -> #REF! | M16: =IF(L16*1.0493>$L$2*25,$L$2*25,L16*1.0493) -> #REF! | N16: =+ROUND($L$2*$N$6*I16,2) -> 656.05 | O16: =+IF(M16>$M$2,M16-$M$2,0)*$O$6*I16 -> #REF! | P16: =+ROUND(M16*$P$6*I16,2) -> #REF! | Q16: =+ROUND(M16*$Q$6*I16,2) -> #REF! | R16: =+ROUND(M16*$R$6*I16,2) -> #REF! | S16: =+ROUND(M16*$S$6*I16,2) -> #REF! | T16: =+ROUND(M16*$T$6*I16,2) -> #REF! | U16: =+SUM(N16:T16) -> #REF! | W16: =+ROUND(I16*M16*$W$6,2) -> #REF! | X16: =+ROUND(H16*M16*(VLOOKUP(M16,TABLAS!$B$44:$D$50,3,1)+1.125%),2) -> #REF! | Y16: =+ROUND(H16*M16*$Y$6,2) -> #REF! | Z16: =+SUM(W16:Y16) -> #REF! | AB16: =+U16 -> #REF! | AC16: =+Z16 -> #REF! | AD16: =+H16*L16*3% -> #REF! | AE16: =+SUM(AB16:AD16) -> #REF! | AG16: =+AE16+AJ16 -> #REF! | AH16: =+AG16*16% -> #REF! | AI16: =+AG16+AH16 -> #REF! | AJ16: =+AE16*7.21% -> #REF! | AK16: =AL16*31 -> #REF! | AL16: =AE16/30.4 -> #REF!
A17: =+A16+1 -> 10 | F17: =CALCULO!#REF! -> #REF! | G17: =CALCULO!#REF! -> #REF! | H17: =+I17-J17-K17 -> 31 | I17: 31 | J17: 0 | K17: 0 | L17: =+CALCULO!#REF! -> #REF! | M17: =IF(L17*1.0493>$L$2*25,$L$2*25,L17*1.0493) -> #REF! | N17: =+ROUND($L$2*$N$6*I17,2) -> 656.05 | O17: =+IF(M17>$M$2,M17-$M$2,0)*$O$6*I17 -> #REF! | P17: =+ROUND(M17*$P$6*I17,2) -> #REF! | Q17: =+ROUND(M17*$Q$6*I17,2) -> #REF! | R17: =+ROUND(M17*$R$6*I17,2) -> #REF! | S17: =+ROUND(M17*$S$6*I17,2) -> #REF! | T17: =+ROUND(M17*$T$6*I17,2) -> #REF! | U17: =+SUM(N17:T17) -> #REF! | W17: =+ROUND(I17*M17*$W$6,2) -> #REF! | X17: =+ROUND(H17*M17*(VLOOKUP(M17,TABLAS!$B$44:$D$50,3,1)+1.125%),2) -> #REF! | Y17: =+ROUND(H17*M17*$Y$6,2) -> #REF! | Z17: =+SUM(W17:Y17) -> #REF! | AB17: =+U17 -> #REF! | AC17: =+Z17 -> #REF! | AD17: =+H17*L17*3% -> #REF! | AE17: =+SUM(AB17:AD17) -> #REF! | AG17: =+AE17+AJ17 -> #REF! | AH17: =+AG17*16% -> #REF! | AI17: =+AG17+AH17 -> #REF! | AJ17: =+AE17*7.21% -> #REF! | AK17: =AL17*31 -> #REF! | AL17: =AE17/30.4 -> #REF!
A18: =+A17+1 -> 11 | F18: =CALCULO!#REF! -> #REF! | G18: =CALCULO!#REF! -> #REF! | H18: =+I18-J18-K18 -> 31 | I18: 31 | J18: 0 | K18: 0 | L18: =+CALCULO!#REF! -> #REF! | M18: =IF(L18*1.0493>$L$2*25,$L$2*25,L18*1.0493) -> #REF! | N18: =+ROUND($L$2*$N$6*I18,2) -> 656.05 | O18: =+IF(M18>$M$2,M18-$M$2,0)*$O$6*I18 -> #REF! | P18: =+ROUND(M18*$P$6*I18,2) -> #REF! | Q18: =+ROUND(M18*$Q$6*I18,2) -> #REF! | R18: =+ROUND(M18*$R$6*I18,2) -> #REF! | S18: =+ROUND(M18*$S$6*I18,2) -> #REF! | T18: =+ROUND(M18*$T$6*I18,2) -> #REF! | U18: =+SUM(N18:T18) -> #REF! | W18: =+ROUND(I18*M18*$W$6,2) -> #REF! | X18: =+ROUND(H18*M18*(VLOOKUP(M18,TABLAS!$B$44:$D$50,3,1)+1.125%),2) -> #REF! | Y18: =+ROUND(H18*M18*$Y$6,2) -> #REF! | Z18: =+SUM(W18:Y18) -> #REF! | AB18: =+U18 -> #REF! | AC18: =+Z18 -> #REF! | AD18: =+H18*L18*3% -> #REF! | AE18: =+SUM(AB18:AD18) -> #REF! | AG18: =+AE18+AJ18 -> #REF! | AH18: =+AG18*16% -> #REF! | AI18: =+AG18+AH18 -> #REF! | AJ18: =+AE18*7.21% -> #REF! | AK18: =AL18*31 -> #REF! | AL18: =AE18/30.4 -> #REF!
A19: =+A18+1 -> 12 | F19: =CALCULO!#REF! -> #REF! | G19: =CALCULO!#REF! -> #REF! | H19: =+I19-J19-K19 -> 31 | I19: 31 | J19: 0 | K19: 0 | L19: =+CALCULO!#REF! -> #REF! | M19: =IF(L19*1.0493>$L$2*25,$L$2*25,L19*1.0493) -> #REF! | N19: =+ROUND($L$2*$N$6*I19,2) -> 656.05 | O19: =+IF(M19>$M$2,M19-$M$2,0)*$O$6*I19 -> #REF! | P19: =+ROUND(M19*$P$6*I19,2) -> #REF! | Q19: =+ROUND(M19*$Q$6*I19,2) -> #REF! | R19: =+ROUND(M19*$R$6*I19,2) -> #REF! | S19: =+ROUND(M19*$S$6*I19,2) -> #REF! | T19: =+ROUND(M19*$T$6*I19,2) -> #REF! | U19: =+SUM(N19:T19) -> #REF! | W19: =+ROUND(I19*M19*$W$6,2) -> #REF! | X19: =+ROUND(H19*M19*(VLOOKUP(M19,TABLAS!$B$44:$D$50,3,1)+1.125%),2) -> #REF! | Y19: =+ROUND(H19*M19*$Y$6,2) -> #REF! | Z19: =+SUM(W19:Y19) -> #REF! | AB19: =+U19 -> #REF! | AC19: =+Z19 -> #REF! | AD19: =+H19*L19*3% -> #REF! | AE19: =+SUM(AB19:AD19) -> #REF! | AG19: =+AE19+AJ19 -> #REF! | AH19: =+AG19*16% -> #REF! | AI19: =+AG19+AH19 -> #REF! | AJ19: =+AE19*7.21% -> #REF! | AK19: =AL19*31 -> #REF! | AL19: =AE19/30.4 -> #REF!
A20: =+A19+1 -> 13 | F20: =CALCULO!#REF! -> #REF! | G20: =CALCULO!#REF! -> #REF! | H20: =+I20-J20-K20 -> 31 | I20: 31 | J20: 0 | K20: 0 | L20: =+CALCULO!#REF! -> #REF! | M20: =IF(L20*1.0493>$L$2*25,$L$2*25,L20*1.0493) -> #REF! | N20: =+ROUND($L$2*$N$6*I20,2) -> 656.05 | O20: =+IF(M20>$M$2,M20-$M$2,0)*$O$6*I20 -> #REF! | P20: =+ROUND(M20*$P$6*I20,2) -> #REF! | Q20: =+ROUND(M20*$Q$6*I20,2) -> #REF! | R20: =+ROUND(M20*$R$6*I20,2) -> #REF! | S20: =+ROUND(M20*$S$6*I20,2) -> #REF! | T20: =+ROUND(M20*$T$6*I20,2) -> #REF! | U20: =+SUM(N20:T20) -> #REF! | W20: =+ROUND(I20*M20*$W$6,2) -> #REF! | X20: =+ROUND(H20*M20*(VLOOKUP(M20,TABLAS!$B$44:$D$50,3,1)+1.125%),2) -> #REF! | Y20: =+ROUND(H20*M20*$Y$6,2) -> #REF! | Z20: =+SUM(W20:Y20) -> #REF! | AB20: =+U20 -> #REF! | AC20: =+Z20 -> #REF! | AD20: =+H20*L20*3% -> #REF! | AE20: =+SUM(AB20:AD20) -> #REF! | AG20: =+AE20+AJ20 -> #REF! | AH20: =+AG20*16% -> #REF! | AI20: =+AG20+AH20 -> #REF! | AJ20: =+AE20*7.21% -> #REF! | AK20: =AL20*31 -> #REF! | AL20: =AE20/30.4 -> #REF!
... A189: =+A188+1 -> 182 | F189: =CALCULO!#REF! -> #REF! | G189: =CALCULO!#REF! -> #REF! | H189: =+I189-J189-K189 -> 31 | I189: 31 | J189: 0 | K189: 0 | L189: =+CALCULO!#REF! -> #REF! | M189: =IF(L189*1.0493>$L$2*25,$L$2*25,L189*1.0493) -> #REF! | N189: =+ROUND($L$2*$N$6*I189,2) -> 656.05 | O189: =+IF(M189>$M$2,M189-$M$2,0)*$O$6*I189 -> #REF! | P189: =+ROUND(M189*$P$6*I189,2) -> #REF! | Q189: =+ROUND(M189*$Q$6*I189,2) -> #REF! | R189: =+ROUND(M189*$R$6*I189,2) -> #REF! | S189: =+ROUND(M189*$S$6*I189,2) -> #REF! | T189: =+ROUND(M189*$T$6*I189,2) -> #REF! | U189: =+SUM(N189:T189) -> #REF! | W189: =+ROUND(I189*M189*$W$6,2) -> #REF! | X189: =+ROUND(H189*M189*(VLOOKUP(M189,TABLAS!$B$44:$D$50,3,1)+1.125%),2) -> #REF! | Y189: =+ROUND(H189*M189*$Y$6,2) -> #REF! | Z189: =+SUM(W189:Y189) -> #REF! | AB189: =+U189 -> #REF! | AC189: =+Z189 -> #REF! | AD189: =+H189*L189*3% -> #REF! | AE189: =+SUM(AB189:AD189) -> #REF! | AG189: =+AE189+AJ189 -> #REF! | AH189: =+AG189*16% -> #REF! | AI189: =+AG189+AH189 -> #REF! | AJ189: =+AE189*7.21% -> #REF! | AK189: =AL189*31 -> #REF! | AL189: =AE189/30.4 -> #REF!
F191: SUMA | H191: =+SUM(H8:H189) -> 5642 | N191: =+SUM(N8:N189) -> 119401.1 | O191: =+SUM(O8:O189) -> #REF! | P191: =+SUM(P8:P189) -> #REF! | Q191: =+SUM(Q8:Q189) -> #REF! | R191: =+SUM(R8:R189) -> #REF! | S191: =+SUM(S8:S189) -> #REF! | T191: =+SUM(T8:T189) -> #REF! | U191: =+SUM(U8:U189) -> #REF! | ... AE191: =+SUM(AE8:AE189) -> #REF! | AG191: =+SUM(AG8:AG9) -> #REF! | AI191: =+SUM(AI8:AI9) -> #REF! | AJ191: =+SUM(AJ8:AJ9) -> #REF!
AJ193: =+AJ191*2 -> #REF!

Sheet Hoja1
A1: N° | B1: NOMBRE | C1: CLAVE | D1: TOTAL DEPOSITO | E1: DIAS | F1: SALARIO DIARIO | G1: SUELDO | H1: ART 113 | I1: SUBSIDIO | J1: SUBSIDIO AL EMPLEO | K1: ISR | L1: VASA | M1: SINDICATO | N1: COSTO SOCIAL
A4: 1 | B4: MELO CAMPA EDGAR | C4: DIRECCIÓN GENERAL | D4: 15000 | E4: 31 | F4: 180 | G4: =+E4*F4 -> 5580 | H4: =(G4-VLOOKUP(G4,TABLAS!$A$7:$D$14,1))*VLOOKUP(G4,TABLAS!$A$7:$D$14,4)+VLOOKUP(G4,TABLAS!$A$7:$D$14,3) -> 319.2856 | I4: =+VLOOKUP(G4,TABLAS!$A$28:$C$38,3) -> #N/A | J4: =+IF(I4>H4,I4-H4,0) -> #N/A | K4: =+IF(H4>I4,H4-I4,0) -> #N/A | L4: =+G4+J4-K4 -> #N/A | M4: =+D4-L4 -> #N/A | N4: =+IMSS!AG8 -> #REF!
A5: 2 | B5: VERGARA BAUTISTA OSCAR | C5: JEFE DE INFORMACIÓN | D5: 9000 | E5: 31 | F5: 130 | G5: =+E5*F5 -> 4030 | H5: =(G5-VLOOKUP(G5,TABLAS!$A$7:$D$14,1))*VLOOKUP(G5,TABLAS!$A$7:$D$14,4)+VLOOKUP(G5,TABLAS!$A$7:$D$14,3) -> 220.0856 | I5: =+VLOOKUP(G5,TABLAS!$A$28:$C$38,3) -> #N/A | J5: =+IF(I5>H5,I5-H5,0) -> #N/A | K5: =+IF(H5>I5,H5-I5,0) -> #N/A | L5: =+G5+J5-K5 -> #N/A | M5: =+D5-L5 -> #N/A | N5: =+IMSS!AG9 -> #REF!
A6: 3 | B6: ALVAREZ FLORES ROBERTO | C6: REPORTERO | D6: 6000 | E6: 31 | F6: 90 | G6: =+E6*F6 -> 2790 | H6: =(G6-VLOOKUP(G6,TABLAS!$A$7:$D$14,1))*VLOOKUP(G6,TABLAS!$A$7:$D$14,4)+VLOOKUP(G6,TABLAS!$A$7:$D$14,3) -> 140.7256 | I6: =+VLOOKUP(G6,TABLAS!$A$28:$C$38,3) -> #N/A | J6: =+IF(I6>H6,I6-H6,0) -> #N/A | K6: =+IF(H6>I6,H6-I6,0) -> #N/A | L6: =+G6+J6-K6 -> #N/A | M6: =+D6-L6 -> #N/A | N6: =+IMSS!#REF! -> #REF!
A7: 4 | B7: GARCÍA HDEZ. TANIA NEREYDA | C7: REPORTERO | D7: 6000 | E7: 31 | F7: 90 | G7: =+E7*F7 -> 2790 | H7: =(G7-VLOOKUP(G7,TABLAS!$A$7:$D$14,1))*VLOOKUP(G7,TABLAS!$A$7:$D$14,4)+VLOOKUP(G7,TABLAS!$A$7:$D$14,3) -> 140.7256 | I7: =+VLOOKUP(G7,TABLAS!$A$28:$C$38,3) -> #N/A | J7: =+IF(I7>H7,I7-H7,0) -> #N/A | K7: =+IF(H7>I7,H7-I7,0) -> #N/A | L7: =+G7+J7-K7 -> #N/A | M7: =+D7-L7 -> #N/A | N7: =+IMSS!#REF! -> #REF!
A8: 5 | B8: MARTINEZ MEDINA DAVID ABRAHAM | C8: REPORTERO | D8: 6000 | E8: 31 | F8: 90 | G8: =+E8*F8 -> 2790 | H8: =(G8-VLOOKUP(G8,TABLAS!$A$7:$D$14,1))*VLOOKUP(G8,TABLAS!$A$7:$D$14,4)+VLOOKUP(G8,TABLAS!$A$7:$D$14,3) -> 140.7256 | I8: =+VLOOKUP(G8,TABLAS!$A$28:$C$38,3) -> #N/A | J8: =+IF(I8>H8,I8-H8,0) -> #N/A | K8: =+IF(H8>I8,H8-I8,0) -> #N/A | L8: =+G8+J8-K8 -> #N/A | M8: =+D8-L8 -> #N/A | N8: =+IMSS!#REF! -> #REF!
A9: 6 | B9: HDEZ. RICARDEZ JORGE ADRIÁN | C9: REPORTERO | D9: 4000 | E9: 31 | F9: 90 | G9: =+E9*F9 -> 2790 | H9: =(G9-VLOOKUP(G9,TABLAS!$A$7:$D$14,1))*VLOOKUP(G9,TABLAS!$A$7:$D$14,4)+VLOOKUP(G9,TABLAS!$A$7:$D$14,3) -> 140.7256 | I9: =+VLOOKUP(G9,TABLAS!$A$28:$C$38,3) -> #N/A | J9: =+IF(I9>H9,I9-H9,0) -> #N/A | K9: =+IF(H9>I9,H9-I9,0) -> #N/A | L9: =+G9+J9-K9 -> #N/A | M9: =+D9-L9 -> #N/A | N9: =+IMSS!#REF! -> #REF!
A10: 7 | B10: RODRÍGUEZ ACEVEDO ALFONSO | C10: REPORTERO | D10: 6000 | E10: 31 | F10: 90 | G10: =+E10*F10 -> 2790 | H10: =(G10-VLOOKUP(G10,TABLAS!$A$7:$D$14,1))*VLOOKUP(G10,TABLAS!$A$7:$D$14,4)+VLOOKUP(G10,TABLAS!$A$7:$D$14,3) -> 140.7256 | I10: =+VLOOKUP(G10,TABLAS!$A$28:$C$38,3) -> #N/A | J10: =+IF(I10>H10,I10-H10,0) -> #N/A | K10: =+IF(H10>I10,H10-I10,0) -> #N/A | L10: =+G10+J10-K10 -> #N/A | M10: =+D10-L10 -> #N/A | N10: =+IMSS!#REF! -> #REF!
A11: 8 | B11: SALAZAR RUEDA YANIBIA | C11: REPORTERO | D11: 7000 | E11: 31 | F11: 90 | G11: =+E11*F11 -> 2790 | H11: =(G11-VLOOKUP(G11,TABLAS!$A$7:$D$14,1))*VLOOKUP(G11,TABLAS!$A$7:$D$14,4)+VLOOKUP(G11,TABLAS!$A$7:$D$14,3) -> 140.7256 | I11: =+VLOOKUP(G11,TABLAS!$A$28:$C$38,3) -> #N/A | J11: =+IF(I11>H11,I11-H11,0) -> #N/A | K11: =+IF(H11>I11,H11-I11,0) -> #N/A | L11: =+G11+J11-K11 -> #N/A | M11: =+D11-L11 -> #N/A | N11: =+IMSS!#REF! -> #REF!
A12: 9 | B12: HUMBERTO CRUZ | C12: CONDUCTOR | D12: 10000 | E12: 31 | F12: 162.92 | G12: =+E12*F12 -> 5050.52 | H12: =(G12-VLOOKUP(G12,TABLAS!$A$7:$D$14,1))*VLOOKUP(G12,TABLAS!$A$7:$D$14,4)+VLOOKUP(G12,TABLAS!$A$7:$D$14,3) -> 285.39888 | I12: =+VLOOKUP(G12,TABLAS!$A$28:$C$38,3) -> #N/A | J12: =+IF(I12>H12,I12-H12,0) -> #N/A | K12: =+IF(H12>I12,H12-I12,0) -> #N/A | L12: =+G12+J12-K12 -> #N/A | M12: =+D12-L12 -> #N/A | N12: =+IMSS!#REF! -> #REF!
A13: 10 | B13: CORTÉS MENDEZ JOSÉ DE JESÚS | C13: CAMARÓGRAFO | D13: 4000 | E13: 31 | F13: 80.8 | G13: =+E13*F13 -> 2504.8 | H13: =(G13-VLOOKUP(G13,TABLAS!$A$7:$D$14,1))*VLOOKUP(G13,TABLAS!$A$7:$D$14,4)+VLOOKUP(G13,TABLAS!$A$7:$D$14,3) -> 122.4728 | I13: =+VLOOKUP(G13,TABLAS!$A$28:$C$38,3) -> #N/A | J13: =+IF(I13>H13,I13-H13,0) -> #N/A | K13: =+IF(H13>I13,H13-I13,0) -> #N/A | L13: =+G13+J13-K13 -> #N/A | M13: =+D13-L13 -> #N/A | N13: =+IMSS!#REF! -> #REF!
A14: 11 | B14: CRUZ ALONSO EVARISTO | C14: CAMARÓGRAFO | D14: 7000 | E14: 31 | F14: 80.8 | G14: =+E14*F14 -> 2504.8 | H14: =(G14-VLOOKUP(G14,TABLAS!$A$7:$D$14,1))*VLOOKUP(G14,TABLAS!$A$7:$D$14,4)+VLOOKUP(G14,TABLAS!$A$7:$D$14,3) -> 122.4728 | I14: =+VLOOKUP(G14,TABLAS!$A$28:$C$38,3) -> #N/A | J14: =+IF(I14>H14,I14-H14,0) -> #N/A | K14: =+IF(H14>I14,H14-I14,0) -> #N/A | L14: =+G14+J14-K14 -> #N/A | M14: =+D14-L14 -> #N/A | N14: =+IMSS!#REF! -> #REF!
A15: 12 | B15: DÍAZ MEOÑO MARIANA | C15: CAMARÓGRAFO | D15: 6000 | E15: 31 | F15: 80.8 | G15: =+E15*F15 -> 2504.8 | H15: =(G15-VLOOKUP(G15,TABLAS!$A$7:$D$14,1))*VLOOKUP(G15,TABLAS!$A$7:$D$14,4)+VLOOKUP(G15,TABLAS!$A$7:$D$14,3) -> 122.4728 | I15: =+VLOOKUP(G15,TABLAS!$A$28:$C$38,3) -> #N/A | J15: =+IF(I15>H15,I15-H15,0) -> #N/A | K15: =+IF(H15>I15,H15-I15,0) -> #N/A | L15: =+G15+J15-K15 -> #N/A | M15: =+D15-L15 -> #N/A | N15: =+IMSS!#REF! -> #REF!
A16: 13 | B16: MARTÍNEZ MORALES ADÁN | C16: CAMARÓGRAFO | D16: 6000 | E16: 31 | F16: 80.8 | G16: =+E16*F16 -> 2504.8 | H16: =(G16-VLOOKUP(G16,TABLAS!$A$7:$D$14,1))*VLOOKUP(G16,TABLAS!$A$7:$D$14,4)+VLOOKUP(G16,TABLAS!$A$7:$D$14,3) -> 122.4728 | I16: =+VLOOKUP(G16,TABLAS!$A$28:$C$38,3) -> #N/A | J16: =+IF(I16>H16,I16-H16,0) -> #N/A | K16: =+IF(H16>I16,H16-I16,0) -> #N/A | L16: =+G16+J16-K16 -> #N/A | M16: =+D16-L16 -> #N/A | N16: =+IMSS!#REF! -> #REF!
A17: 14 | B17: RAMÍREZ CERVANTES EDUARDO | C17: CAMARÓGRAFO | D17: 7000 | E17: 31 | F17: 80.8 | G17: =+E17*F17 -> 2504.8 | H17: =(G17-VLOOKUP(G17,TABLAS!$A$7:$D$14,1))*VLOOKUP(G17,TABLAS!$A$7:$D$14,4)+VLOOKUP(G17,TABLAS!$A$7:$D$14,3) -> 122.4728 | I17: =+VLOOKUP(G17,TABLAS!$A$28:$C$38,3) -> #N/A | J17: =+IF(I17>H17,I17-H17,0) -> #N/A | K17: =+IF(H17>I17,H17-I17,0) -> #N/A | L17: =+G17+J17-K17 -> #N/A | M17: =+D17-L17 -> #N/A | N17: =+IMSS!#REF! -> #REF!
... A41: 38 | B41: QUINTERO RAMÍREZ ANILÚ | C41: SIN PUESTO | D41: 10000 | E41: 31 | F41: 80.8 | G41: =+E41*F41 -> 2504.8 | H41: =(G41-VLOOKUP(G41,TABLAS!$A$7:$D$14,1))*VLOOKUP(G41,TABLAS!$A$7:$D$14,4)+VLOOKUP(G41,TABLAS!$A$7:$D$14,3) -> 122.4728 | I41: =+VLOOKUP(G41,TABLAS!$A$28:$C$38,3) -> #N/A | J41: =+IF(I41>H41,I41-H41,0) -> #N/A | K41: =+IF(H41>I41,H41-I41,0) -> #N/A | L41: =+G41+J41-K41 -> #N/A | M41: =+D41-L41 -> #N/A | N41: =+IMSS!#REF! -> #REF!
B43: SUMA | D43: =+SUM(D4:D41) -> 239600 | E43: =+SUM(E4:E41) -> 1178 | G43: =+SUM(G4:G41) -> 104997 | J43: =+SUM(J4:J41) -> #N/A | K43: =+SUM(K4:K41) -> #N/A | L43: =+SUM(L4:L41) -> #N/A | M43: =+SUM(M4:M41) -> #N/A | N43: =SUM(N4:N41) -> #REF!
L45: =+L43+M43 -> #N/A
G48: TOTAL
I49: IMSS | K49: VASA | L49: BEN SIND | N49: TOTAL
J50: NOMINA | K50: =+L43 -> #N/A | L50: =+M43 -> #N/A | N50: =+K50+L50 -> #N/A
I51: =I50*6% -> 0 | J51: COMISION 6.5% | K51: =K50*6.5% -> #N/A | L51: =L50*6.5% -> #N/A | N51: =+K51+L51 -> #N/A
J52: COSTO IMSS | K52: =+N43 -> #REF! | N52: =+K52 -> #REF!
J53: SUBTOTAL | N53: =+N50+N51+N52 -> #N/A
J54: IVA 16% | N54: =N53*0.16 -> #N/A
I55: =I53+I54 -> 0 | J55: TOTAL DEPOSITO | K55: =K53+K54 -> 0 | L55: =+L50+L51 -> #N/A | N55: =N53+N54 -> #N/A
